{
  "$schema": "https://schema.management.azure.com/schemas/2019-04-01/deploymentParameters.json#",
  "contentVersion": "1.0.0.0",
  "parameters": {
    "parTopLevelManagementGroupPrefix": {
      "value": "psc"
    },
    "parTopLevelManagementGroupSuffix": {
      "value": ""
    },
    "parIntRootMgSubs": {
      "value": []
    },
    "parPlatformMgSubs": {
      "value": []
    },
    "parPlatformManagementMgSubs": {
      "value": []
    },
    "parPlatformConnectivityMgSubs": {
      "value": [
        "a3ad735d-1e81-41fc-b57d-134f2c2bd403"
      ]
    },
    "parPlatformIdentityMgSubs": {
      "value": [
        "951196a7-69c5-45fa-b853-9c96817bd007"
      ]
    },
    "parLandingZonesMgSubs": {
      "value": []
    },
    "parLandingZonesCorpMgSubs": {
      "value": [
        "e4b60627-c354-4db6-8e7b-aab3e6204415"
    ]
    },
    "parLandingZonesOnlineMgSubs": {
      "value": []
    },
    "parLandingZonesConfidentialCorpMgSubs": {
      "value": []
    },
    "parLandingZonesConfidentialOnlineMgSubs": {
      "value": []
    },
    "parLandingZoneMgChildrenSubs": {
      "value": {}
    },
    "parPlatformMgChildrenSubs": {
      "value": {}
    },
    "parDecommissionedMgSubs": {
      "value": []
    },
    "parSandboxMgSubs": {
      "value": [
        "86fde88b-9e2a-4115-b70c-62c9b83ccdc7"
      ]
    },
    "parTelemetryOptOut": {
      "value": false
    }
  }
}
